Metadata-Version: 2.0
Name: odoo10-addon-l10n-fr-state
Version: 10.0.1.0.0
Summary: Populate Database with French States (Régions)
Home-page: http://www.grap.coop
Author: GRAP,Akretion,Odoo Community Association (OCA)
Author-email: support@odoo-community.org
License: AGPL-3
Platform: UNKNOWN
Requires-Dist: odoo (<10.1dev,>=10.0)
Classifier: Programming Language :: Python :: 2.7
Classifier: Framework :: Odoo
Classifier: License :: OSI Approved :: GNU Affero General Public License v3
